{
    "title": "PIGSTY",
    "description": "FOSS Database Distribution",
    "root": true,
    "icon": "Castle",
    "pages": [
        "index",
        "intro",
        "module",
        "compare",

        "---Installation---",
        "install",
        "slim",
        "offline",
        "linux",

        "---Deployment---",
        "prepare",
        "security",
        "vagrant",
        "terraform",

        "--- ---",
        "author",
        "history",
        "license",
        "community",
        "release",
        "event",
        "cve",
        "..."
    ]
}